Metadata-Version: 2.1
Name: trendln
Version: 0.1.8
Summary: Support and Resistance Trend lines Calculator for Financial Analysis
Home-page: https://github.com/GregoryMorse/trendln
Author: Gregory Morse
Author-email: gregory.morse@live.com
License: MIT
Keywords: trendlines,trend lines,trend,support,resistance,trends,technical,indicators,financial,analysis
Platform: any
Classifier: License :: OSI Approved :: MIT License
Classifier: Development Status :: 5 - Production/Stable
Classifier: Operating System :: OS Independent
Classifier: Intended Audience :: Developers
Classifier: Topic :: Office/Business :: Financial
Classifier: Topic :: Office/Business :: Financial :: Investment
Classifier: Topic :: Software Development :: Libraries
Classifier: Topic :: Software Development :: Libraries :: Python Modules
Classifier: Programming Language :: Python :: 2.7
Classifier: Programming Language :: Python :: 3.4
Classifier: Programming Language :: Python :: 3.5
Classifier: Programming Language :: Python :: 3.6
Classifier: Programming Language :: Python :: 3.7
